foveatorch/__init__.py
foveatorch/modfoveate.py
foveatorch/neopyramid.py
foveatorch-0.1.8.dist-info/LICENSE
foveatorch-0.1.8.dist-info/METADATA
foveatorch-0.1.8.dist-info/WHEEL
foveatorch-0.1.8.dist-info/top_level.txt
foveatorch-0.1.8.dist-info/zip-safe
foveatorch-0.1.8.dist-info/RECORD
