Metadata-Version: 2.1
Name: foveatorch
Version: 0.1.8
Summary: Differentiable foveated vision for Deep Learning methods
Home-page: https://github.com/emaballarin/foveatorch
Author: Emanuele Ballarin
Author-email: emanuele@ballarin.cc
License: MIT
Keywords: Deep Learning,Machine Learning,Computer Vision,Computational Neuroscience,Differentiable Programming
Classifier: Development Status :: 4 - Beta
Classifier: Topic :: Scientific/Engineering :: Artificial Intelligence
Classifier: Environment :: Console
Classifier: Programming Language :: Python :: 3
Classifier: License :: OSI Approved :: MIT License
Requires-Python: >=3.10
License-File: LICENSE
Requires-Dist: torch >=2
Requires-Dist: kornia >=0.6.12
